{
    "AX": {
        "error": 0.10302037919070568, 
        "fit": "average_SEM", 
        "value": -0.018542551930780367
    }, 
    "CDD": {
        "error": 0.0002502678836628824, 
        "fit": "average_SEM", 
        "value": 0.00040681154763054413
    }, 
    "H1": {
        "error": 0.142218766862209, 
        "fit": "average_SEM", 
        "value": 0.06540106852808095
    }, 
    "H2": {
        "error": 0.1208892349153985, 
        "fit": "average_SEM", 
        "value": 0.22285688831858957
    }, 
    "L1": {
        "error": 0.18752265469870114, 
        "fit": "average_SEM", 
        "value": -0.06160549876901011
    }, 
    "L2": {
        "error": 0.13257835281594338, 
        "fit": "average_SEM", 
        "value": -0.07817433136539573
    }
}