{
    "AX": {
        "error": 0.058025058027187666, 
        "fit": "average_SEM", 
        "value": -0.011304029244638514
    }, 
    "CDD": {
        "error": 3.402583532384326e-05, 
        "fit": "average_SEM", 
        "value": 7.773468678351491e-06
    }, 
    "H1": {
        "error": 0.11590527365088199, 
        "fit": "average_SEM", 
        "value": 0.049856117214585535
    }, 
    "H2": {
        "error": 0.11414593742313532, 
        "fit": "average_SEM", 
        "value": 0.2321050546132028
    }, 
    "L1": {
        "error": 0.20831960813976513, 
        "fit": "average_SEM", 
        "value": -0.06999384879527497
    }, 
    "L2": {
        "error": 0.14454487213388195, 
        "fit": "average_SEM", 
        "value": -0.06301303240761627
    }
}