{
    "AX": {
        "error": 0.05867300856461726, 
        "fit": "average_SEM", 
        "value": -0.011834141795892114
    }, 
    "CDD": {
        "error": 6.252340438197083e-05, 
        "fit": "average_SEM", 
        "value": 2.3320406035054476e-05
    }, 
    "H1": {
        "error": 0.13562957768094094, 
        "fit": "average_SEM", 
        "value": 0.06158593361518191
    }, 
    "H2": {
        "error": 0.11733840910381173, 
        "fit": "average_SEM", 
        "value": -0.029394175399728637
    }, 
    "L1": {
        "error": 0.19427042658612426, 
        "fit": "average_SEM", 
        "value": -0.05454724076617923
    }, 
    "L2": {
        "error": 0.14328318228054707, 
        "fit": "average_SEM", 
        "value": -0.02993646561614393
    }
}