{
    "AX": {
        "error": 0.0626890413290244, 
        "fit": "average_SEM", 
        "value": -0.04040721020246565
    }, 
    "CDD": {
        "error": 0.00013544886153135202, 
        "fit": "average_SEM", 
        "value": 0.00010494182764280898
    }, 
    "H1": {
        "error": 0.11371207893023812, 
        "fit": "average_SEM", 
        "value": 0.018815908847318496
    }, 
    "H2": {
        "error": 0.12093720956924729, 
        "fit": "average_SEM", 
        "value": -0.2904858322348446
    }, 
    "L1": {
        "error": 0.15444978113380986, 
        "fit": "average_SEM", 
        "value": -0.08727402462003132
    }, 
    "L2": {
        "error": 0.15350472314658334, 
        "fit": "average_SEM", 
        "value": -0.016967725231855486
    }
}