{
    "Ar36": {
        "error": 0.0066680332241398198, 
        "fit": "parabolic", 
        "value": 0.31565064502793932
    }, 
    "Ar37": {
        "error": 0.13159581755333535, 
        "fit": "linear", 
        "value": -0.0060094868319423723
    }, 
    "Ar38": {
        "error": 0.16961860319766342, 
        "fit": "linear", 
        "value": -0.03912520506037101
    }, 
    "Ar39": {
        "error": 0.059072464868197408, 
        "fit": "parabolic", 
        "value": 0.0081648194705056538
    }, 
    "Ar40": {
        "error": 0.18023489750196084, 
        "fit": "parabolic", 
        "value": 95.979544745723842
    }, 
    "Ar41": {
        "error": 0.12853794803629146, 
        "fit": "average_SEM", 
        "value": -0.38458088081446479
    }
}